<annotation>
	<folder>train</folder>
	<filename>left_b3230.jpg</filename>
	<path>/root/autoware_auto_thesis/tensorflow/workspace/ssd_vehicle_detection/images/train/left_b3230.jpg</path>
	<source>
		<database>Unknown</database>
	</source>
	<size>
		<width>640</width>
		<height>360</height>
		<depth>3</depth>
	</size>
	<segmented>0</segmented>
	<object>
		<name>car</name>
		<pose>Unspecified</pose>
		<truncated>0</truncated>
		<difficult>0</difficult>
		<bndbox>
			<xmin>274</xmin>
			<ymin>184</ymin>
			<xmax>318</xmax>
			<ymax>213</ymax>
		</bndbox>
	</object>
	<object>
		<name>car</name>
		<pose>Unspecified</pose>
		<truncated>0</truncated>
		<difficult>0</difficult>
		<bndbox>
			<xmin>368</xmin>
			<ymin>186</ymin>
			<xmax>404</xmax>
			<ymax>214</ymax>
		</bndbox>
	</object>
	<object>
		<name>car</name>
		<pose>Unspecified</pose>
		<truncated>0</truncated>
		<difficult>0</difficult>
		<bndbox>
			<xmin>317</xmin>
			<ymin>191</ymin>
			<xmax>359</xmax>
			<ymax>223</ymax>
		</bndbox>
	</object>
	<object>
		<name>car</name>
		<pose>Unspecified</pose>
		<truncated>0</truncated>
		<difficult>0</difficult>
		<bndbox>
			<xmin>320</xmin>
			<ymin>185</ymin>
			<xmax>342</xmax>
			<ymax>199</ymax>
		</bndbox>
	</object>
</annotation>
